footings/__init__.py
footings/assumption_registry.py
footings/audit.py
footings/data_dictionary.py
footings/exceptions.py
footings/factories.py
footings/io/__init__.py
footings/io/from_json.py
footings/io/from_xlsx.py
footings/io/to_json.py
footings/io/to_xlsx.py
footings/jigs.py
footings/model.py
footings/scenario_registry.py
footings/testing.py
footings/utils.py
footings/validators.py
footings/visualize.py
footings-0.11.0.dist-info/LICENSE
footings-0.11.0.dist-info/WHEEL
footings-0.11.0.dist-info/METADATA
footings-0.11.0.dist-info/RECORD
