Metadata-Version: 2.1
Name: footings
Version: 0.11.0
Summary: A model building library
Home-page: https://github.com/footings/footings
License: BSD 3-Clause License
Author: Dustin Tindall
Author-email: dustin.tindall@gmail.com
Requires-Python: >=3.7,<4.0
Classifier: License :: OSI Approved :: BSD License
Classifier: License :: Other/Proprietary License
Classifier: Programming Language :: Python :: 3
Classifier: Programming Language :: Python :: 3.7
Classifier: Programming Language :: Python :: 3.8
Classifier: Programming Language :: Python :: 3.9
Requires-Dist: attrs (>=20.0,<21.0)
Requires-Dist: importlib-metadata (>=3.0,<4.0); python_version < "3.8"
Requires-Dist: numpy (>=1.11,<2.0)
Requires-Dist: openpyxl (>=3.0,<4.0)
Requires-Dist: pandas (>=1.0,<2.0)
Project-URL: Documentation, https://footings.github.io/footings/
Project-URL: Repository, https://github.com/footings/footings
